{
    "users": [
        {
            "name": "Amaduesz",
            "hash": "310056"
        },
        {
            "name": "Remek",
            "hash": "420420"
        },
        {
            "name": "Ola",
            "hash": "123456"
        },
        {
            "name": "Kacper",
            "hash": "123457"
        },
        {
            "name": "Igor",
            "hash": "123458"
        },
        {
            "name": "Karolina",
            "hash": "123459"
        },
        {
            "name": "Szymon",
            "hash": "123460"
        },
        {
            "name": "Kto\u0139\u203a",
            "hash": "123461"
        },
        {
            "name": "Jeszcze kto\u0139\u203a",
            "hash": "123462"
        },
        {
            "name": "Ziomek",
            "hash": "123463"
        },
        {
            "name": "Ziomu\u0139\u203a",
            "hash": "123464"
        },
        {
            "name": "WOW",
            "hash": "123465"
        },
        {
            "name": "dlkawmlkfdmalkef",
            "hash": "810151"
        },
        {
            "name": "Wuja",
            "hash": "106956"
        },
        {
            "name": "Kozak",
            "hash": "197188"
        },
        {
            "name": "Cwiertnia",
            "hash": "634188"
        }
    ]
}